{"id":"y51b7","Variables":{"Identifiants":"y51b7;0383239P;572","IdentifiantsSearch":"Paysage:y51b7|UAI:0383239P","CONDEVT":"(382271X27X814TOUS = 'Y')","RecherchePublique":"Y","Origine":"Non renseigné","TypeOrigine":"Non renseigné","Etat":"Actif","Libelle":"Observatoire des sciences de l'univers de Grenoble - Université Grenoble Alpes","Libelle2":"Observatoire des sciences de l'univers de Grenoble - Université Grenoble Alpes","SigleNom":"Observatoire des sciences de l'univers de Grenoble - Université Grenoble Alpes","Denominations":"Observatoire des sciences de l'univers de Grenoble - Université Grenoble Alpes","Denominations2":"NomLong:Observatoire des sciences de l'univers de Grenoble - Université Grenoble Alpes","NomOfficiel":"","NomsOfficiels":"","NbNomsOfficiels":1,"Categorie":"Observatoire","tokenCategorie":"i4O23","tokenCategoriesActives":"xDiLg;Ma7Zh;LZvm0;bj2S3","CategoriesActives":"Structure de la région Auvergne-Rhône-Alpes;Structure de l'académie de Grenoble;Structure de l'Isère;Structure de l'unité urbaine Grenoble","AutresParentsActuels":0,"tokenParentsActifs":"Y7ch7","Parents":"Y7ch7","Coordonnees":"45.193766473681,5.7608760823753","NbIdentifiants":2,"PremIdentifiants":"UAI","UAI":"0383239P","Annelis":"https://dgesip-annelis.adc.education.fr/etablissement/572","NbSitesExternes":1,"ALId":"572","SitePrinc":"y51b7"},"EtatCivil":{"id":"4792","token":"y51b7","submitdate":"2019-04-17 17:37:29","lastpage":"1","startlanguage":"fr","startdate":"2019-04-17 17:37:29","datestamp":"2019-04-17 17:37:29","392782X88X1357":"N","392782X88X1277":"O","392782X88X1294":"N","392782X88X1292":"N","392782X88X1326":"N","392782X88X1281":"0000-00-00 00:00:00","392782X88X1293":"N","etat":"O","date2app":"N","TypeOrigine":"Non renseigné"},"Verification":{"Predecesseur":"N","Successeur":"N","TitreIng":"N","Fondation":"N","RectoratViceRectorat":"N","Parent":"N"},"Etat":"A","Potentielle":"N","Rubriques":{"Identifiants":{"Aff":"O"},"Portrait":{"Aff":"O","Identite":{"Aff":"O","Tutelles":{"Aff":"O","token":"09QPX"},"Parent":{"Aff":"O"}},"Coordonnees":{"Aff":"O","Carte":{"Aff":"O"},"Addresse":{"Aff":"O"}},"Internet":{"Aff":"O","Annelis":{"Aff":"O"}}},"Evenements":{"Aff":"O"},"TxtOff":{"Aff":"O","BO":{"Aff":"O"}},"Gouvernance":{"Aff":"O"},"Liste":{"Aff":"O"}},"Identifiant":{"Paysage":[{"Id":"y51b7","etat":"A"}],"UAI":[{"Id":"0383239P","id":"300041","token":"y51b79w","submitdate":"2019-04-17 17:37:29","lastpage":"1","startlanguage":"fr","startdate":"2019-04-17 17:37:29","datestamp":"2019-04-17 17:37:29","ipaddr":"193.50.162.131","934142X50X696":"y51b7","934142X50X561":"UAI","934142X50X562":"0383239P","934142X50X566":"A","934142X50X657":"N","934142X50X658":"N","etat":"A"}],"ALId":[{"Id":"572","Lien":"https://dgesip-annelis.adc.education.fr/etablissement/572","id":"342177","token":"y51b7Xb","submitdate":"2022-03-18 10:53:20","lastpage":"1","startlanguage":"fr","startdate":"2022-03-18 10:53:17","datestamp":"2022-03-18 10:53:17","ipaddr":"193.48.4.6","934142X50X1798":"Structure","934142X50X696":"y51b7","934142X50X561":"ALId","934142X50X2755":"572","934142X50X566":"A","etat":"A"}]},"Denominations":[{"id":"4769","token":"y51b731","submitdate":"2019-04-17 17:37:29","lastpage":"1","startlanguage":"fr","startdate":"2019-04-17 17:37:29","datestamp":"2019-04-17 17:37:29","494486X85X1260":"y51b7","494486X85X1359":"N","494486X85X1261":"Observatoire des sciences de l'univers de Grenoble - Université Grenoble Alpes","494486X85X1254":"I","494486X85X1322":"N","494486X85X1258":"N","494486X85X1330":"N","494486X85X1255":"0000-00-00 00:00:00","494486X85X1259":"N","etat":"I","date2app":"N","Libelle":"Observatoire des sciences de l'univers de Grenoble - Université Grenoble Alpes","Libelle2":"Observatoire des sciences de l'univers de Grenoble - Université Grenoble Alpes"}],"Categorie":[{"id":"37688","token":"lcMxALI","submitdate":"2019-04-17 17:37:29","lastpage":"2","startlanguage":"fr","startdate":"2019-04-17 17:37:29","datestamp":"2019-04-17 17:37:29","341716X100X2216":"i4O2372","341716X100X2190":"CC","341716X100X2189":"i4O23","341716X100X2191":"G5R9d","341716X100X2214":"S","341716X100X1979":"y51b7","341716X100X1998":"N","341716X100X1968":"A","341716X100X1994":"N","341716X100X1995":"0.0000000000","341716X100X1977":"N","341716X100X2196":"XXXXX","341716X100X1996":"N","341716X100X1978":"N","341716X100X2197":"XXXXX","341716X100X2210":"N","341716X100X2213":"N","tokenParent":"i4O23","tokenReseau":"i4O2372","tokenLiaison":"G5R9d","tokenEnfant":"y51b7","date1App":"N","etat":"A","ordre":"20.0000000000","Parent":"Observatoire","Liaison":"Appartient à la liste","Enfant":"Observatoire des sciences de l'univers de Grenoble - Université Grenoble Alpes"},{"tokenReseau":"xDiLgZZ","tokenParent":"xDiLg","tokenLiaison":"G5R9d","341716X100X1979":"y51b7","tokenEnfant":"y51b7","341716X100X2190":"CC","ordre":"500.0000000000","etat":"A","id":"1452","Parent":"Structure de la région Auvergne-Rhône-Alpes","Liaison":"Appartient à la liste","Enfant":"Observatoire des sciences de l'univers de Grenoble - Université Grenoble Alpes"},{"tokenReseau":"Ma7ZhZZ","tokenParent":"Ma7Zh","tokenLiaison":"G5R9d","341716X100X1979":"y51b7","tokenEnfant":"y51b7","341716X100X2190":"CC","ordre":"600.0000000000","etat":"A","id":"1452","Parent":"Structure de l'académie de Grenoble","Liaison":"Appartient à la liste","Enfant":"Observatoire des sciences de l'univers de Grenoble - Université Grenoble Alpes"},{"tokenReseau":"LZvm0ZZ","tokenParent":"LZvm0","tokenLiaison":"G5R9d","341716X100X1979":"y51b7","tokenEnfant":"y51b7","341716X100X2190":"CC","ordre":"600.0000000000","etat":"A","id":"1452","Parent":"Structure de l'Isère","Liaison":"Appartient à la liste","Enfant":"Observatoire des sciences de l'univers de Grenoble - Université Grenoble Alpes"},{"tokenReseau":"bj2S3ZZ","tokenParent":"bj2S3","tokenLiaison":"G5R9d","341716X100X1979":"y51b7","tokenEnfant":"y51b7","341716X100X2190":"CC","ordre":"600.0000000000","etat":"A","id":"1452","Parent":"Structure de l'unité urbaine Grenoble","Liaison":"Appartient à la liste","Enfant":"Observatoire des sciences de l'univers de Grenoble - Université Grenoble Alpes"}],"Tutelle":[{"id":"39263","token":"9M3972k","submitdate":"2019-05-24 13:48:08","lastpage":"2","startlanguage":"fr","startdate":"2019-05-24 13:48:08","datestamp":"2019-05-24 13:48:08","341716X100X2216":"09QPXHG","341716X100X2190":"CT","341716X100X2189":"09QPX","341716X100X2191":"G5R9d","341716X100X2214":"S","341716X100X1979":"y51b7","341716X100X1998":"N","341716X100X1968":"A","341716X100X1994":"N","341716X100X1995":"0.0000000000","341716X100X1977":"N","341716X100X2196":"XXXXX","341716X100X1996":"N","341716X100X1978":"N","341716X100X2197":"XXXXX","341716X100X2210":"N","341716X100X2213":"N","tokenParent":"09QPX","tokenReseau":"09QPXHG","tokenLiaison":"G5R9d","tokenEnfant":"y51b7","date1App":"N","etat":"A","ordre":"1.0000000000","Parent":"ministre chargé de l'enseignement supérieur","Liaison":"Appartient à la liste","Enfant":"Observatoire des sciences de l'univers de Grenoble - Université Grenoble Alpes"}],"Parents":[{"id":"82641","token":"r22Qqv2","submitdate":"2021-06-04 09:43:10","lastpage":"2","startlanguage":"fr","startdate":"2021-06-04 09:43:10","datestamp":"2021-06-04 09:43:10","341716X100X2216":"Y7ch75g","341716X100X2190":"P","341716X100X2189":"Y7ch7","341716X100X2191":"AKjLD","341716X100X2214":"S","341716X100X1979":"y51b7","341716X100X1998":"N","341716X100X1999":"N","341716X100X2193":"N","341716X100X1968":"A","341716X100X1994":"N","341716X100X1977":"N","341716X100X2196":"XXXXX","341716X100X1996":"N","341716X100X1978":"N","341716X100X2210":"N","tokenParent":"Y7ch7","tokenReseau":"Y7ch75g","tokenLiaison":"AKjLD","tokenEnfant":"y51b7","date1App":"N","date2App":"N","date3App":"N","etat":"A","Parent":"Université Grenoble Alpes","Liaison":"Parent","Enfant":"Observatoire des sciences de l'univers de Grenoble - Université Grenoble Alpes"}],"Localisation":[{"Localisation":"PoT5g","id":"4717","token":"y51b710","submitdate":"2019-05-24 13:48:08","lastpage":"1","startlanguage":"fr","startdate":"2019-05-24 13:48:08","datestamp":"2019-05-24 13:48:08","ipaddr":"193.50.162.131","353588X52X699":"y51b7","353588X52X1002":"S","353588X52X760":"A1","353588X52X592":"PoT5g","353588X52X1000":"Saint-Martin-d'Hères","353588X52X644":"38421","353588X52X595ADD":"414 rue DE LA PISCINE","353588X52X595LD":"Domaine universitaire","353588X52X595CP":"38400","353588X52X595LOC":"ST MARTIN D HERES","353588X52X595PAYS":"France","353588X52X762":"0476514981","353588X52X593":"45.193766473681,5.7608760823753","353588X52X589":"A","353588X52X1377":"N","353588X52X1379":"N","etat":"A","gps":"45.193766473681,5.7608760823753","adresse":"414 rue DE LA PISCINE, Domaine universitaire, 38400 ST MARTIN D HERES","com_code":"38421","com_nom":"Saint-Martin-d'Hères","uucr_id":"UU38701","uucr_nom":"Grenoble","agglo":"Grenoble","dep_id":"D038","dep_nom_num":"Isère (38)","dep_nom":"Isère","aca_id":"A08","aca_nom":"Grenoble","aca_nom2":"Académie de Grenoble","reg_nom_old":"Rhône-Alpes","reg_id_old":"R82","reg_id":"R84","reg_nom":"Auvergne-Rhône-Alpes","SelLocalisation":"Auvergne-Rhône-Alpes>Grenoble>Isère>Saint-Martin-d'Hères"}],"Localisations":{"com_code":"38421","com_nom":"Saint-Martin-d'Hères","uucr_id":"UU38701","uucr_nom":"Grenoble","agglo":"Grenoble","dep_id":"D038","dep_nom_num":"Isère (38)","dep_nom":"Isère","aca_id":"A08","aca_nom":"Grenoble","reg_id":"R84","reg_nom":"Auvergne-Rhône-Alpes"},"Evenement":[{"id":"13491","token":"DbcUV22v1eAVLXK","submitdate":"2021-06-04 09:31:19","lastpage":"1","startlanguage":"fr","seed":"825266905","startdate":"2021-06-04 09:25:18","datestamp":"2022-03-18 16:16:51","ipaddr":"86.252.203.182","refurl":"https://paysage.mesri.fr/","227593X28X942":"DbcUV","227593X28X943":"y51b7","227593X28X1334":"2021-05-10 00:00:00","227593X28X1395":"N","227593X28X988":"d6a2Oamu","227593X28X1335":"N","227593X28X327":"2021-05-10 00:00:00","227593X28X328":"N","227593X28X344":"N","227593X28X1217":"Directrice de l’observatoire des sciences de l’univers de Grenoble","227593X30X1447":"arret","227593X30X1188":"BOESR","227593X30X1189":"22.0000000000","227593X30X351":"https://www.enseignementsup-recherche.gouv.fr/fr/bo/21/Hebdo22/ESRS2115170A.htm","227593X30X375":"Directrice de l’observatoire des sciences de l’univers de Grenoble","227593X30X1823nomination":"Y","227593X30X1786":"N","227593X30X352":"ESRS2115170A","227593X30X354":"2021-05-10 00:00:00","227593X30X355":"2021-05-11 00:00:00","227593X30X1450":"Voir sur esr.gouv.fr","227593X30X1451":"https://www.enseignementsup-recherche.gouv.fr/fr/bo/21/Hebdo22/ESRS2115170A.htm","227593X30X1452":"Directrice de l’observatoire des sciences de l’univers de Grenoble","date1":"2021-05-10 00:00:00","date1app":"N","txtofflien":"https://www.enseignementsup-recherche.gouv.fr/fr/bo/21/Hebdo22/ESRS2115170A.htm","txtofflib":"Directrice de l’observatoire des sciences de l’univers de Grenoble"}],"TxtOff":{"BO":[{"id":"13491","token":"DbcUV22v1eAVLXK","submitdate":"2021-06-04 09:31:19","lastpage":"1","startlanguage":"fr","seed":"825266905","startdate":"2021-06-04 09:25:18","datestamp":"2022-03-18 16:16:51","ipaddr":"86.252.203.182","refurl":"https://paysage.mesri.fr/","227593X28X942":"DbcUV","227593X28X943":"y51b7","227593X28X1334":"2021-05-10 00:00:00","227593X28X1395":"N","227593X28X988":"d6a2Oamu","227593X28X1335":"N","227593X28X327":"2021-05-10 00:00:00","227593X28X328":"N","227593X28X344":"N","227593X28X1217":"Directrice de l’observatoire des sciences de l’univers de Grenoble","227593X30X1447":"arret","227593X30X1188":"BOESR","227593X30X1189":"22.0000000000","227593X30X351":"https://www.enseignementsup-recherche.gouv.fr/fr/bo/21/Hebdo22/ESRS2115170A.htm","227593X30X375":"Directrice de l’observatoire des sciences de l’univers de Grenoble","227593X30X1823nomination":"Y","227593X30X1786":"N","227593X30X352":"ESRS2115170A","227593X30X354":"2021-05-10 00:00:00","227593X30X355":"2021-05-11 00:00:00","227593X30X1450":"Voir sur esr.gouv.fr","227593X30X1451":"https://www.enseignementsup-recherche.gouv.fr/fr/bo/21/Hebdo22/ESRS2115170A.htm","227593X30X1452":"Directrice de l’observatoire des sciences de l’univers de Grenoble","date1":"2021-05-10 00:00:00","date1app":"N","txtofflien":"https://www.enseignementsup-recherche.gouv.fr/fr/bo/21/Hebdo22/ESRS2115170A.htm","txtofflib":"Directrice de l’observatoire des sciences de l’univers de Grenoble"}]},"Gouvernance":[{"id":"82634","token":"xF2Ng6Q","submitdate":"2021-06-04 09:32:31","lastpage":"2","startlanguage":"fr","startdate":"2021-06-04 09:32:31","datestamp":"2021-06-04 09:32:31","341716X100X2216":"y51b7LR","341716X100X2190":"G","341716X100X2189":"y51b7","341716X100X2191":"aa77J","341716X100X2214":"P","341716X100X1979":"DbcUV","341716X100X1992":"2021-05-10 00:00:00","341716X100X1998":"N","341716X100X1999":"N","341716X100X2193":"N","341716X100X1968":"A","341716X100X2208":"SO","341716X100X1994":"N","341716X100X1970":"2021-05-10 00:00:00","341716X100X1977":"N","341716X100X2227":"SO","341716X100X1996":"N","341716X100X1978":"N","341716X100X2210":"N","tokenParent":"y51b7","tokenReseau":"y51b7LR","tokenLiaison":"aa77J","tokenEnfant":"DbcUV","date1":"2021-05-10 00:00:00","date1App":"N","date2App":"N","date3App":"N","etat":"A","Parent":"Observatoire des sciences de l'univers de Grenoble - Université Grenoble Alpes","Enfant":"Nathalie Cotte","Liaison":"Directrice","Telephone":""}],"Liste":{"y51b7y2":{"id":"8939","token":"y51b7y2","submitdate":"2021-06-04 09:41:40","lastpage":"1","startlanguage":"fr","startdate":"2021-06-04 09:41:40","datestamp":"2021-06-04 09:41:40","785856X72X1056":"y51b7","785856X72X2223":"CM","785856X72X1076":"Contact MESRI","785856X72X1049":"A","785856X72X1871":"Personne","tokenParent":"y51b7","typeListe":"CM"},"y51b7LR":{"id":"8938","token":"y51b7LR","submitdate":"2021-06-04 09:32:31","lastpage":"1","startlanguage":"fr","startdate":"2021-06-04 09:32:31","datestamp":"2021-06-04 09:32:31","785856X72X1056":"y51b7","785856X72X2223":"G","785856X72X1076":"Gouvernance","785856X72X1049":"A","785856X72X1871":"Personne","tokenParent":"y51b7","typeListe":"G","Liste":[{"tokenParent":"y51b7","tokenReseau":"y51b7LR","tokenEnfant":"DbcUV","tokenLiaison":"aa77J","date1":"2021-05-10 00:00:00","date1app":"N","date2app":"N","date3app":"N","etat":"A","id":"82634","token":"xF2Ng6Q","submitdate":"2021-06-04 09:32:31","lastpage":"2","startlanguage":"fr","startdate":"2021-06-04 09:32:31","datestamp":"2021-06-04 09:32:31","341716X100X2216":"y51b7LR","341716X100X2190":"G","341716X100X2189":"y51b7","341716X100X2191":"aa77J","341716X100X2214":"P","341716X100X1979":"DbcUV","341716X100X1992":"2021-05-10 00:00:00","341716X100X1998":"N","341716X100X1999":"N","341716X100X2193":"N","341716X100X1968":"A","341716X100X2208":"SO","341716X100X1994":"N","341716X100X1970":"2021-05-10 00:00:00","341716X100X1977":"N","341716X100X2227":"SO","341716X100X1996":"N","341716X100X1978":"N","341716X100X2210":"N","Parent":"Observatoire des sciences de l'univers de Grenoble - Université Grenoble Alpes","Enfant":"Nathalie Cotte","Liaison":"Directrice"}]}},"DansListe":[{"tokenParent":"09QPX","tokenReseau":"09QPXHG","tokenEnfant":"y51b7","tokenLiaison":"G5R9d","date1app":"N","etat":"A","id":"39263","token":"9M3972k","submitdate":"2019-05-24 13:48:08","lastpage":"2","startlanguage":"fr","startdate":"2019-05-24 13:48:08","datestamp":"2019-05-24 13:48:08","341716X100X2216":"09QPXHG","341716X100X2190":"CT","341716X100X2189":"09QPX","341716X100X2191":"G5R9d","341716X100X2214":"S","341716X100X1979":"y51b7","341716X100X1998":"N","341716X100X1968":"A","341716X100X1994":"N","341716X100X1995":"0.0000000000","341716X100X1977":"N","341716X100X2196":"XXXXX","341716X100X1996":"N","341716X100X1978":"N","341716X100X2197":"XXXXX","341716X100X2210":"N","341716X100X2213":"N","Parent":"ministre chargé de l'enseignement supérieur","Enfant":"Observatoire des sciences de l'univers de Grenoble - Université Grenoble Alpes","Liaison":"Appartient à la liste","gps":"45.193766473681,5.7608760823753","Liste":{"id":"1222","token":"09QPXHG","submitdate":"2020-05-22 09:42:42","lastpage":"1","startlanguage":"fr","startdate":"2020-05-22 09:42:42","datestamp":"2020-05-22 09:42:42","785856X72X1056":"09QPX","785856X72X2223":"CT","785856X72X1076":"Liste","785856X72X1049":"A","785856X72X1871":"Structure","tokenParent":"09QPX","typeListe":"CT"}},{"tokenParent":"i4O23","tokenReseau":"i4O2372","tokenEnfant":"y51b7","tokenLiaison":"G5R9d","date1app":"N","etat":"A","id":"37688","token":"lcMxALI","submitdate":"2019-04-17 17:37:29","lastpage":"2","startlanguage":"fr","startdate":"2019-04-17 17:37:29","datestamp":"2019-04-17 17:37:29","341716X100X2216":"i4O2372","341716X100X2190":"CC","341716X100X2189":"i4O23","341716X100X2191":"G5R9d","341716X100X2214":"S","341716X100X1979":"y51b7","341716X100X1998":"N","341716X100X1968":"A","341716X100X1994":"N","341716X100X1995":"0.0000000000","341716X100X1977":"N","341716X100X2196":"XXXXX","341716X100X1996":"N","341716X100X1978":"N","341716X100X2197":"XXXXX","341716X100X2210":"N","341716X100X2213":"N","Parent":"Observatoire","Enfant":"Observatoire des sciences de l'univers de Grenoble - Université Grenoble Alpes","Liaison":"Appartient à la liste","gps":"45.193766473681,5.7608760823753","Liste":{"id":"1534","token":"i4O2372","submitdate":"2020-06-02 16:07:23","lastpage":"1","startlanguage":"fr","startdate":"2020-06-02 16:07:23","datestamp":"2020-06-02 16:07:23","785856X72X1056":"i4O23","785856X72X2223":"CC","785856X72X1076":"Liste","785856X72X1049":"A","785856X72X1871":"Structure","tokenParent":"i4O23","typeListe":"CC"}},{"tokenParent":"Y7ch7","tokenReseau":"Y7ch75g","tokenEnfant":"y51b7","tokenLiaison":"AKjLD","date1app":"N","date2app":"N","date3app":"N","etat":"A","id":"82641","token":"r22Qqv2","submitdate":"2021-06-04 09:43:10","lastpage":"2","startlanguage":"fr","startdate":"2021-06-04 09:43:10","datestamp":"2021-06-04 09:43:10","341716X100X2216":"Y7ch75g","341716X100X2190":"P","341716X100X2189":"Y7ch7","341716X100X2191":"AKjLD","341716X100X2214":"S","341716X100X1979":"y51b7","341716X100X1998":"N","341716X100X1999":"N","341716X100X2193":"N","341716X100X1968":"A","341716X100X1994":"N","341716X100X1977":"N","341716X100X2196":"XXXXX","341716X100X1996":"N","341716X100X1978":"N","341716X100X2210":"N","Parent":"Université Grenoble Alpes","Enfant":"Observatoire des sciences de l'univers de Grenoble - Université Grenoble Alpes","Liaison":"Parent","gps":"45.193766473681,5.7608760823753","Liste":{"id":"2576","token":"Y7ch75g","submitdate":"2020-08-24 14:17:07","lastpage":"1","startlanguage":"fr","startdate":"2020-08-24 14:17:07","datestamp":"2020-08-24 14:17:07","785856X72X1056":"Y7ch7","785856X72X2223":"P","785856X72X1076":"Structures internes","785856X72X1049":"A","785856X72X1871":"Structure","tokenParent":"Y7ch7","typeListe":"P"}},{"tokenReseau":"xDiLgZZ","tokenParent":"xDiLg","tokenLiaison":"G5R9d","341716X100X1979":"y51b7","tokenEnfant":"y51b7","341716X100X2190":"CC","ordre":"500.0000000000","etat":"A","id":"1452","Parent":"Structure de la région Auvergne-Rhône-Alpes","Enfant":"Observatoire des sciences de l'univers de Grenoble - Université Grenoble Alpes","Liaison":"Appartient à la liste","gps":"45.193766473681,5.7608760823753","Liste":{"token":"xDiLgZZ","785856X72X1056":"xDiLg","tokenParent":"xDiLg","typeListe":"CC","785856X72X1871":"A","785856X72X1076":"Liste des structures"}},{"tokenReseau":"Ma7ZhZZ","tokenParent":"Ma7Zh","tokenLiaison":"G5R9d","341716X100X1979":"y51b7","tokenEnfant":"y51b7","341716X100X2190":"CC","ordre":"600.0000000000","etat":"A","id":"1452","Parent":"Structure de l'académie de Grenoble","Enfant":"Observatoire des sciences de l'univers de Grenoble - Université Grenoble Alpes","Liaison":"Appartient à la liste","gps":"45.193766473681,5.7608760823753","Liste":{"token":"Ma7ZhZZ","785856X72X1056":"Ma7Zh","tokenParent":"Ma7Zh","typeListe":"CC","785856X72X1871":"A","785856X72X1076":"Liste des structures"}},{"tokenReseau":"LZvm0ZZ","tokenParent":"LZvm0","tokenLiaison":"G5R9d","341716X100X1979":"y51b7","tokenEnfant":"y51b7","341716X100X2190":"CC","ordre":"600.0000000000","etat":"A","id":"1452","Parent":"Structure de l'Isère","Enfant":"Observatoire des sciences de l'univers de Grenoble - Université Grenoble Alpes","Liaison":"Appartient à la liste","gps":"45.193766473681,5.7608760823753","Liste":{"token":"LZvm0ZZ","785856X72X1056":"LZvm0","tokenParent":"LZvm0","typeListe":"CC","785856X72X1871":"A","785856X72X1076":"Liste des structures"}},{"tokenReseau":"bj2S3ZZ","tokenParent":"bj2S3","tokenLiaison":"G5R9d","341716X100X1979":"y51b7","tokenEnfant":"y51b7","341716X100X2190":"CC","ordre":"600.0000000000","etat":"A","id":"1452","Parent":"Structure de l'unité urbaine Grenoble","Enfant":"Observatoire des sciences de l'univers de Grenoble - Université Grenoble Alpes","Liaison":"Appartient à la liste","gps":"45.193766473681,5.7608760823753","Liste":{"token":"bj2S3ZZ","785856X72X1056":"bj2S3","tokenParent":"bj2S3","typeListe":"CC","785856X72X1871":"A","785856X72X1076":"Liste des structures"}}],"Attributs":{"attribute_1":"291JP","attribute_2":"291JP","attribute_3":"2022-03-18 10:53:20","attribute_4":"Observatoire des sciences de l'univers de Grenoble - Université Grenoble Alpes","attribute_5":"Structure","attribute_6":"Observatoire","attribute_9":"A","attribute_13":"y51b7;0383239P;572","attribute_14":"Observatoire des sciences de l'univers de Grenoble - Université Grenoble Alpes","attribute_15":"Observatoire des sciences de l'univers de Grenoble - Université Grenoble Alpes","attribute_16":"45.193766473681,5.7608760823753","attribute_17":"Auvergne-Rhône-Alpes","attribute_18":"Grenoble","attribute_19":"Isère (38)","attribute_20":"Grenoble","attribute_21":"Saint-Martin-d'Hères","attribute_24":"Y7ch7","attribute_28":"45.193766473681","attribute_29":"5.7608760823753","attribute_31":"y51b7","attribute_33":"0383239P","attribute_36":"Observatoire des sciences de l'univers de Grenoble - Université Grenoble Alpes","attribute_49":"y51b731","attribute_50":"414 rue DE LA PISCINE, Domaine universitaire, 38400 ST MARTIN D HERES","attribute_54":"Université Grenoble Alpes","attribute_55":"0383239P","attribute_56":"Grenoble","attribute_57":"Auvergne-Rhône-Alpes","attribute_61":"Non renseigné","attribute_63":"38421","attribute_66":"R84","attribute_67":"A08","attribute_68":"Y7ch7","attribute_80":"--observatoire-des-sciences-de-l-univers-de-grenoble-universite-grenoble-alpes--","attribute_81":"Y","attribute_86":"i4O23","attribute_92":"D038","attribute_94":"Grenoble","attribute_95":"UU38701","attribute_96":"Isère","attribute_99":"Paysage:y51b7|UAI:0383239P","attribute_100":"NomLong:Observatoire des sciences de l'univers de Grenoble - Université Grenoble Alpes","attribute_101":"2022-03-18 11:25:43","attribute_108":"Structure de la région Auvergne-Rhône-Alpes;Structure de l'académie de Grenoble;Structure de l'Isère;Structure de l'unité urbaine Grenoble","attribute_109":"xDiLg;Ma7Zh;LZvm0;bj2S3","attribute_110":"Saint-Martin-d'Hères","attribute_119":"2022-01-26 19:07:41","attribute_120":"2022-03-18 11:25:59","attribute_123":"572"},"JsonMAJ":"2022-03-21 19:29:02","TypeObjet":"Structure"}